djangocms_stories_agenda/__init__.py
djangocms_stories_agenda/admin.py
djangocms_stories_agenda/apps.py
djangocms_stories_agenda/cms_plugins.py
djangocms_stories_agenda/misc.py
djangocms_stories_agenda/models.py
djangocms_stories_agenda/patched_urls.py
djangocms_stories_agenda/signals.py
djangocms_stories_agenda/utils.py
djangocms_stories_agenda/views.py
djangocms_stories_agenda/conf/__init__.py
djangocms_stories_agenda/conf/settings.py
djangocms_stories_agenda/locale/fr/LC_MESSAGES/django.mo
djangocms_stories_agenda/locale/fr/LC_MESSAGES/django.po
djangocms_stories_agenda/migrations/0001_squashed_0009_postextension_is_pinned_and_more.py
djangocms_stories_agenda/migrations/0010_remove_upcomingeventsplugin_show_until_event_end_and_more.py
djangocms_stories_agenda/migrations/__init__.py
djangocms_stories_agenda/templates/djangocms_stories/plugins/djangocms_stories_agenda/archive.html
djangocms_stories_agenda/templates/djangocms_stories/plugins/djangocms_stories_agenda/categories.html
djangocms_stories_agenda/templates/djangocms_stories/plugins/djangocms_stories_agenda/tags.html
djangocms_stories_agenda/templates/djangocms_stories_agenda/blog_meta.html
djangocms_stories_agenda/templates/djangocms_stories_agenda/post_detail.html
djangocms_stories_agenda/templates/djangocms_stories_agenda/post_item.html
djangocms_stories_agenda/templates/djangocms_stories_agenda/post_list.html
djangocms_stories_agenda/templates/djangocms_stories_agenda/includes/item_with_counter.html
djangocms_stories_agenda/tests/__init__.py
djangocms_stories_agenda/tests/conftest.py
djangocms_stories_agenda/tests/settings.py
djangocms_stories_agenda/tests/test_views.py
djangocms_stories_agenda-0.1.6.dist-info/licenses/AUTHORS.md
djangocms_stories_agenda-0.1.6.dist-info/licenses/LICENSE
djangocms_stories_agenda-0.1.6.dist-info/METADATA
djangocms_stories_agenda-0.1.6.dist-info/WHEEL
djangocms_stories_agenda-0.1.6.dist-info/top_level.txt
djangocms_stories_agenda-0.1.6.dist-info/RECORD
