Metadata-Version: 2.4
Name: djangocms-stories-agenda
Version: 0.1.6
Summary: Create an agenda on top of djangocms-stories!
Home-page: https://gitlab.com/kapt/open-source/djangocms-stories-agenda
Author: Corentin Bettiol, Adrien Delhorme
Author-email: dev@kapt.mobi
Classifier: Environment :: Web Environment
Classifier: Framework :: Django
Classifier: Framework :: Django CMS
Classifier: Intended Audience :: Developers
Classifier: License :: OSI Approved :: GNU General Public License v3 (GPLv3)
Classifier: Programming Language :: Python
Classifier: Programming Language :: Python :: 3
Classifier: Topic :: Internet :: WWW/HTTP
Classifier: Topic :: Internet :: WWW/HTTP :: Dynamic Content
Classifier: Framework :: Django CMS :: 4.0
Classifier: Framework :: Django CMS :: 4.1
Classifier: Framework :: Django CMS :: 5.0
Classifier: Framework :: Django CMS :: 5.1
License-File: LICENSE
License-File: AUTHORS.md
Requires-Dist: djangocms-stories
Requires-Dist: aldryn-apphooks-config>=0.7.0
Requires-Dist: django-appdata>=0.4.0
Requires-Dist: django-recurrence
Provides-Extra: test
Requires-Dist: pytest>=7.0.0; extra == "test"
Requires-Dist: pytest-django>=4.5.2; extra == "test"
Requires-Dist: pytest-cov>=4.0.0; extra == "test"
Dynamic: license-file
